django_sso_client_oauth/__init__.py
django_sso_client_oauth/apps.py
django_sso_client_oauth/settings.py
django_sso_client_oauth/urls.py
django_sso_client_oauth/utils.py
django_sso_client_oauth/views.py
django_sso_client_oauth-1.0.0.dist-info/licenses/LICENSE
django_sso_client_oauth-1.0.0.dist-info/METADATA
django_sso_client_oauth-1.0.0.dist-info/WHEEL
django_sso_client_oauth-1.0.0.dist-info/top_level.txt
django_sso_client_oauth-1.0.0.dist-info/RECORD
